{"events": [{"event_id": "786fecac0dd3686e14b356f5", "title": "Dr. Patel", "start_datetime": "2025-12-05T04:00:00Z", "end_datetime": "2025-12-05T05:00:00Z", "organizer": "", "tag": "personal", "description": "Weekly session \u2014 EMDR continuation", "location": "Capitol Wellness Associates, 2100 Capitol Ave, Suite 310", "attendees": [], "attendee_responses": {}}, {"event_id": "d07bb52d4dc2cc802a23ce02", "title": "Dinner at Byung's", "start_datetime": "2025-12-08T04:00:00Z", "end_datetime": "2025-12-08T06:00:00Z", "organizer": "", "tag": "personal", "description": "Korean BBQ \u2014 Hana's favorite night", "location": "Byung Park's residence", "attendees": ["Soomin Choi", "Byung Park", "Hana Choi"], "attendee_responses": {}}, {"event_id": "0cebc71bab8410a2b90d4b63", "title": "Dr. Patel", "start_datetime": "2025-12-12T04:00:00Z", "end_datetime": "2025-12-12T05:00:00Z", "organizer": "", "tag": "personal", "description": "Weekly session \u2014 incident processing block", "location": "Capitol Wellness Associates, 2100 Capitol Ave, Suite 310", "attendees": [], "attendee_responses": {}}, {"event_id": "d1e6df7b7d00969352e93392", "title": "Dr. Patel", "start_datetime": "2025-12-19T04:00:00Z", "end_datetime": "2025-12-19T05:00:00Z", "organizer": "", "tag": "personal", "description": "Weekly session \u2014 anxiety baseline check", "location": "Capitol Wellness Associates, 2100 Capitol Ave, Suite 310", "attendees": [], "attendee_responses": {}}, {"event_id": "dbb5cb414b9e651feb2b309d", "title": "Dr. Patel", "start_datetime": "2025-12-26T04:00:00Z", "end_datetime": "2025-12-26T05:00:00Z", "organizer": "", "tag": "personal", "description": "Weekly session \u2014 sleep + late-night patterns", "location": "Capitol Wellness Associates, 2100 Capitol Ave, Suite 310", "attendees": [], "attendee_responses": {}}, {"event_id": "51e59f1d7382a5f4daa0ddf6", "title": "Dr. Patel", "start_datetime": "2026-01-02T04:00:00Z", "end_datetime": "2026-01-02T05:00:00Z", "organizer": "", "tag": "personal", "description": "Weekly session \u2014 work boundaries discussion", "location": "Capitol Wellness Associates, 2100 Capitol Ave, Suite 310", "attendees": [], "attendee_responses": {}}, {"event_id": "b73f0d482809ffd33732664c", "title": "Little Oaks orientation - toddler room", "start_datetime": "2026-01-03T19:00:00Z", "end_datetime": "2026-01-03T20:00:00Z", "organizer": "", "tag": "personal", "description": "Toddler room orientation meeting", "location": "Little Oaks Learning Center", "attendees": ["Soomin Choi"], "attendee_responses": {}}, {"event_id": "cbe775e39570180ef8339a64", "title": "Dinner at Byung's", "start_datetime": "2026-01-05T04:00:00Z", "end_datetime": "2026-01-05T06:00:00Z", "organizer": "", "tag": "personal", "description": "Birthday-month family dinner", "location": "Byung Park's residence", "attendees": ["Soomin Choi", "Byung Park", "Hana Choi"], "attendee_responses": {}}, {"event_id": "e8dd8a13cf48f5cc18e6cd5d", "title": "Dr. Patel", "start_datetime": "2026-01-09T04:00:00Z", "end_datetime": "2026-01-09T05:00:00Z", "organizer": "", "tag": "personal", "description": "Weekly session \u2014 choir return reflection", "location": "Capitol Wellness Associates, 2100 Capitol Ave, Suite 310", "attendees": [], "attendee_responses": {}}, {"event_id": "25c16cb106a24456a08b118c", "title": "Plumber visit - water heater", "start_datetime": "2026-01-12T20:00:00Z", "end_datetime": "2026-01-12T21:00:00Z", "organizer": "", "tag": "personal", "description": "Dave from Valley Plumbing. Water heater thermostat.", "location": "2415 T Street", "attendees": [], "attendee_responses": {}}, {"event_id": "5c9f1e3a7b0d2c4f8e6a9b1d", "title": "Gym - weights 6:30-9:30 PM", "start_datetime": "2026-01-15T04:30:00Z", "end_datetime": "2026-01-15T07:30:00Z", "organizer": "", "tag": "personal", "description": "Push day \u2014 chest + tris", "location": "24 Hour Fitness", "attendees": [], "attendee_responses": {}}, {"event_id": "fdcfc44547605c4c9278d62b", "title": "Dr. Patel", "start_datetime": "2026-01-16T04:00:00Z", "end_datetime": "2026-01-16T05:00:00Z", "organizer": "", "tag": "personal", "description": "Weekly session \u2014 relationship check-in (Soomin)", "location": "Capitol Wellness Associates, 2100 Capitol Ave, Suite 310", "attendees": [], "attendee_responses": {}}, {"event_id": "73b320db144b12dfe13f5e40", "title": "Hana - Little Oaks (new toddler hours)", "start_datetime": "2026-01-20T18:00:00Z", "end_datetime": "2026-01-21T03:00:00Z", "organizer": "", "tag": "personal", "description": "Mon-Fri 8 AM - 5 PM, toddler room", "location": "Little Oaks Learning Center", "attendees": [], "attendee_responses": {}}, {"event_id": "f15c01a2b3c4d5e6f7a8b9c0", "title": "Hana 2yr checkup - Dr. Chen", "start_datetime": "2026-01-20T20:00:00Z", "end_datetime": "2026-01-20T21:00:00Z", "organizer": "", "tag": "personal", "description": "10 AM appointment. Bring immunization record.", "location": "Sacramento Pediatrics, 2800 L Street, Suite 120", "attendees": ["Soomin Choi"], "attendee_responses": {}}, {"event_id": "6d0a2f4b8c1e3d5a9f7b0c2e", "title": "Gym - weights 6:30-9:30 PM", "start_datetime": "2026-01-22T04:30:00Z", "end_datetime": "2026-01-22T07:30:00Z", "organizer": "", "tag": "personal", "description": "Pull day \u2014 back + bis", "location": "24 Hour Fitness", "attendees": [], "attendee_responses": {}}, {"event_id": "e0261659355bd4db97a61d02", "title": "Dr. Patel", "start_datetime": "2026-01-23T04:00:00Z", "end_datetime": "2026-01-23T05:00:00Z", "organizer": "", "tag": "personal", "description": "Weekly session \u2014 hypervigilance triggers", "location": "Capitol Wellness Associates, 2100 Capitol Ave, Suite 310", "attendees": [], "attendee_responses": {}}, {"event_id": "9b7072e20c023d5ccc76350b", "title": "Gym - weights 6:30-9:30 PM", "start_datetime": "2026-01-28T04:30:00Z", "end_datetime": "2026-01-28T07:30:00Z", "organizer": "", "tag": "personal", "description": "Leg day \u2014 squats + posterior chain", "location": "24 Hour Fitness", "attendees": [], "attendee_responses": {}}, {"event_id": "d43f81e0a2070e073ce8a4e5", "title": "Dr. Patel", "start_datetime": "2026-01-30T04:00:00Z", "end_datetime": "2026-01-30T05:00:00Z", "organizer": "", "tag": "personal", "description": "Weekly session \u2014 coping strategies refresh", "location": "Capitol Wellness Associates, 2100 Capitol Ave, Suite 310", "attendees": [], "attendee_responses": {}}, {"event_id": "01934defc8a1f4831a63fc69", "title": "Dinner at Byung's", "start_datetime": "2026-02-02T04:00:00Z", "end_datetime": "2026-02-02T06:00:00Z", "organizer": "", "tag": "personal", "description": "Galbi-jjim + side dishes", "location": "Byung Park's residence", "attendees": ["Soomin Choi", "Byung Park", "Hana Choi"], "attendee_responses": {}}, {"event_id": "8688cb25f73ddd56fae79fa1", "title": "Gym - weights 6:30-9:30 PM", "start_datetime": "2026-02-04T04:30:00Z", "end_datetime": "2026-02-04T07:30:00Z", "organizer": "", "tag": "personal", "description": "Push day \u2014 overhead press focus", "location": "24 Hour Fitness", "attendees": [], "attendee_responses": {}}, {"event_id": "7e1b3a5c9d2f4e6b0a8c1d3f", "title": "Gym - weights 6:30-9:30 PM", "start_datetime": "2026-02-05T04:30:00Z", "end_datetime": "2026-02-05T07:30:00Z", "organizer": "", "tag": "personal", "description": "Pull day \u2014 pull-ups + rows", "location": "24 Hour Fitness", "attendees": [], "attendee_responses": {}}, {"event_id": "fcae5feb3744fdbafb31cd86", "title": "Dr. Patel", "start_datetime": "2026-02-06T04:00:00Z", "end_datetime": "2026-02-06T05:00:00Z", "organizer": "", "tag": "personal", "description": "Weekly session \u2014 medication efficacy review", "location": "Capitol Wellness Associates, 2100 Capitol Ave, Suite 310", "attendees": [], "attendee_responses": {}}, {"event_id": "a453f17719bdcea35e6381ce", "title": "Gym - weights 6:30-9:30 PM", "start_datetime": "2026-02-11T04:30:00Z", "end_datetime": "2026-02-11T07:30:00Z", "organizer": "", "tag": "personal", "description": "Leg day \u2014 front squats", "location": "24 Hour Fitness", "attendees": [], "attendee_responses": {}}, {"event_id": "e00b92d7ff2f4fa9a543886b", "title": "Dr. Patel", "start_datetime": "2026-02-13T04:00:00Z", "end_datetime": "2026-02-13T05:00:00Z", "organizer": "", "tag": "personal", "description": "Weekly session \u2014 workplace stress", "location": "Capitol Wellness Associates, 2100 Capitol Ave, Suite 310", "attendees": [], "attendee_responses": {}}, {"event_id": "2d5f8a1c4b7e30916d8a2f5c", "title": "Tahoe camping w/ Carson", "start_datetime": "2026-02-15T16:00:00Z", "end_datetime": "2026-02-18T04:00:00Z", "organizer": "", "tag": "personal", "description": "D.L. Bliss State Park, Eagle Point #141. Check-in 2 PM.", "location": "D.L. Bliss State Park, Tahoma, CA", "attendees": ["Carson Reeves"], "attendee_responses": {}}, {"event_id": "3659f6b5e741b91f4a450538", "title": "Gym - weights 6:30-9:30 PM", "start_datetime": "2026-02-18T04:30:00Z", "end_datetime": "2026-02-18T07:30:00Z", "organizer": "", "tag": "personal", "description": "Push day \u2014 bench + accessory", "location": "24 Hour Fitness", "attendees": [], "attendee_responses": {}}, {"event_id": "4e099f22ee3f7e06cf8d556f", "title": "Dr. Patel", "start_datetime": "2026-02-20T04:00:00Z", "end_datetime": "2026-02-20T05:00:00Z", "organizer": "", "tag": "personal", "description": "Weekly session \u2014 fatherhood + Hana", "location": "Capitol Wellness Associates, 2100 Capitol Ave, Suite 310", "attendees": [], "attendee_responses": {}}, {"event_id": "3a7e1c5d9b2f4a8e6c0d3f71", "title": "CE Seminar - DoubleTree Sacramento (Day 1)", "start_datetime": "2026-02-22T15:00:00Z", "end_datetime": "2026-02-23T00:00:00Z", "organizer": "", "tag": "work", "description": "CDA Infection Control and Safety CE Seminar. 8 AM - 5 PM. Registration #CDA-CE-2026-04817.", "location": "DoubleTree by Hilton, 2001 Point West Way, Sacramento", "attendees": ["Lorena Gutierrez"], "attendee_responses": {}}, {"event_id": "4b8f2d6e0c3a5b9f7d1e4a82", "title": "CE Seminar - DoubleTree Sacramento (Day 2)", "start_datetime": "2026-02-23T15:00:00Z", "end_datetime": "2026-02-24T00:00:00Z", "organizer": "", "tag": "work", "description": "CDA Infection Control and Safety CE Seminar. Day 2.", "location": "DoubleTree by Hilton, 2001 Point West Way, Sacramento", "attendees": ["Lorena Gutierrez"], "attendee_responses": {}}, {"event_id": "55356c23bfdba23cea957240", "title": "Gym - weights 6:30-9:30 PM", "start_datetime": "2026-02-25T04:30:00Z", "end_datetime": "2026-02-25T07:30:00Z", "organizer": "", "tag": "personal", "description": "Pull day \u2014 deadlift + back", "location": "24 Hour Fitness", "attendees": [], "attendee_responses": {}}, {"event_id": "744ae30417983019d4f3ba95", "title": "Dr. Patel", "start_datetime": "2026-02-27T04:00:00Z", "end_datetime": "2026-02-27T05:00:00Z", "organizer": "", "tag": "personal", "description": "Weekly session \u2014 sertraline dosage check", "location": "Capitol Wellness Associates, 2100 Capitol Ave, Suite 310", "attendees": [], "attendee_responses": {}}, {"event_id": "39f4fda4de5a67cce2cd4051", "title": "Dinner at Byung's", "start_datetime": "2026-03-02T04:00:00Z", "end_datetime": "2026-03-02T06:00:00Z", "organizer": "", "tag": "personal", "description": "Casual Sunday \u2014 soup + rice", "location": "Byung Park's residence", "attendees": ["Soomin Choi", "Byung Park", "Hana Choi"], "attendee_responses": {}}, {"event_id": "e6a0d2c4f8b6e9a1c3d5f7b0", "title": "Gym - weights 6:30-9:30 PM", "start_datetime": "2026-03-04T04:30:00Z", "end_datetime": "2026-03-04T07:30:00Z", "organizer": "", "tag": "personal", "description": "Leg day \u2014 lunges + glutes", "location": "24 Hour Fitness", "attendees": [], "attendee_responses": {}}, {"event_id": "9d195dda5e7831cebea2b334", "title": "Dr. Patel", "start_datetime": "2026-03-06T04:00:00Z", "end_datetime": "2026-03-06T05:00:00Z", "organizer": "", "tag": "personal", "description": "Weekly session \u2014 group activity reentry", "location": "Capitol Wellness Associates, 2100 Capitol Ave, Suite 310", "attendees": [], "attendee_responses": {}}, {"event_id": "8c0bc743c0eb61e70b41c277", "title": "Gym - weights 6:30-9:30 PM", "start_datetime": "2026-03-11T03:30:00Z", "end_datetime": "2026-03-11T06:30:00Z", "organizer": "", "tag": "personal", "description": "Push day \u2014 dips + shoulders", "location": "24 Hour Fitness", "attendees": [], "attendee_responses": {}}, {"event_id": "fcf9e41e0e5b7d60ac72e073", "title": "Dr. Patel", "start_datetime": "2026-03-13T03:00:00Z", "end_datetime": "2026-03-13T04:00:00Z", "organizer": "", "tag": "personal", "description": "Weekly session \u2014 running + exercise as coping", "location": "Capitol Wellness Associates, 2100 Capitol Ave, Suite 310", "attendees": [], "attendee_responses": {}}, {"event_id": "c4a8e2f1b5d3097c6a1e8b3f", "title": "Lexus service 8:00 AM", "start_datetime": "2026-03-14T17:00:00Z", "end_datetime": "2026-03-14T18:30:00Z", "organizer": "", "tag": "personal", "description": "30K service + check engine light. Drop off at service dept.", "location": "Lexus of Sacramento, 2740 Fulton Ave", "attendees": [], "attendee_responses": {}}, {"event_id": "4674e11815bbf29f60a4cc08", "title": "Gym - weights 6:30-9:30 PM", "start_datetime": "2026-03-18T03:30:00Z", "end_datetime": "2026-03-18T06:30:00Z", "organizer": "", "tag": "personal", "description": "Pull day \u2014 barbell rows", "location": "24 Hour Fitness", "attendees": [], "attendee_responses": {}}, {"event_id": "8f2c4b6d0e3a5f7c1b9d2e4a", "title": "Gym - weights 6:30-9:30 PM", "start_datetime": "2026-03-19T03:30:00Z", "end_datetime": "2026-03-19T06:30:00Z", "organizer": "", "tag": "personal", "description": "Leg day \u2014 Romanian deadlifts", "location": "24 Hour Fitness", "attendees": [], "attendee_responses": {}}, {"event_id": "620be8e6929c409d398fe787", "title": "Dr. Patel", "start_datetime": "2026-03-20T03:00:00Z", "end_datetime": "2026-03-20T04:00:00Z", "organizer": "", "tag": "personal", "description": "Weekly session \u2014 quarterly progress review", "location": "Capitol Wellness Associates, 2100 Capitol Ave, Suite 310", "attendees": [], "attendee_responses": {}}, {"event_id": "5447807d22d1234744d66a40", "title": "Gym - weights 6:30-9:30 PM", "start_datetime": "2026-03-25T03:30:00Z", "end_datetime": "2026-03-25T06:30:00Z", "organizer": "", "tag": "personal", "description": "Push day \u2014 incline bench", "location": "24 Hour Fitness", "attendees": [], "attendee_responses": {}}, {"event_id": "cd101ebbc3397d94b7363d71", "title": "Dr. Patel", "start_datetime": "2026-03-27T03:00:00Z", "end_datetime": "2026-03-27T04:00:00Z", "organizer": "", "tag": "personal", "description": "Weekly session \u2014 boundary-setting role play", "location": "Capitol Wellness Associates, 2100 Capitol Ave, Suite 310", "attendees": [], "attendee_responses": {}}, {"event_id": "bdfa54f5e4b50892a19c3fe1", "title": "Confirm headcount with Kru", "start_datetime": "2026-03-28T18:00:00Z", "end_datetime": "2026-03-28T19:00:00Z", "organizer": "", "tag": "personal", "description": "Call Kru to confirm final headcount for April 11 private dining room reservation", "location": "", "attendees": [], "attendee_responses": {}}, {"event_id": "3fc798f474777e093b833c5b", "title": "Bonobo @ Ace of Spades", "start_datetime": "2026-03-29T05:00:00Z", "end_datetime": "2026-03-29T08:00:00Z", "organizer": "", "tag": "personal", "description": "Bonobo Fragments Tour. Doors 7 PM, show 8 PM. 2 GA tickets.", "location": "Ace of Spades, 1417 R Street", "attendees": ["Carson Reeves"], "attendee_responses": {}}, {"event_id": "9b13b1a86a090049066a9fa9", "title": "Gym - weights 6:30-9:30 PM", "start_datetime": "2026-04-01T03:30:00Z", "end_datetime": "2026-04-01T06:30:00Z", "organizer": "", "tag": "personal", "description": "Pull day \u2014 face pulls + curls", "location": "24 Hour Fitness", "attendees": [], "attendee_responses": {}}, {"event_id": "d4e2f8a1b5c3097d6a2e8b4f", "title": "Tax review meeting - Linda Nakamura", "start_datetime": "2026-04-01T18:00:00Z", "end_datetime": "2026-04-01T19:00:00Z", "organizer": "", "tag": "personal", "description": "Review 2025 personal and practice tax returns before filing.", "location": "Zoom", "attendees": ["Linda Nakamura"], "attendee_responses": {}}, {"event_id": "6414efc3e73ca0d4e3cf1839", "title": "Dr. Patel", "start_datetime": "2026-04-03T03:00:00Z", "end_datetime": "2026-04-03T04:00:00Z", "organizer": "", "tag": "personal", "description": "Weekly session \u2014 exposure plan check", "location": "Capitol Wellness Associates, 2100 Capitol Ave, Suite 310", "attendees": [], "attendee_responses": {}}, {"event_id": "e419e09e187b8453ce520c06", "title": "Finalize playlist for party", "start_datetime": "2026-04-05T18:00:00Z", "end_datetime": "2026-04-05T19:00:00Z", "organizer": "", "tag": "personal", "description": "Put together Spotify playlist for Soomin's party at Kru", "location": "", "attendees": [], "attendee_responses": {}}, {"event_id": "15b7ef11f63646a011c701b2", "title": "Dinner at Byung's", "start_datetime": "2026-04-06T03:00:00Z", "end_datetime": "2026-04-06T05:00:00Z", "organizer": "", "tag": "personal", "description": "Hana asked for jajangmyeon", "location": "Byung Park's residence", "attendees": ["Soomin Choi", "Byung Park", "Hana Choi"], "attendee_responses": {}}, {"event_id": "bf495eee615e0d6ed08d70e7", "title": "Gym - weights 6:30-9:30 PM", "start_datetime": "2026-04-08T03:30:00Z", "end_datetime": "2026-04-08T06:30:00Z", "organizer": "", "tag": "personal", "description": "Leg day \u2014 hack squats", "location": "24 Hour Fitness", "attendees": [], "attendee_responses": {}}, {"event_id": "3a398f96fce1bfd255ec3190", "title": "Dr. Patel", "start_datetime": "2026-04-10T03:00:00Z", "end_datetime": "2026-04-10T04:00:00Z", "organizer": "", "tag": "personal", "description": "Weekly session \u2014 values alignment work", "location": "Capitol Wellness Associates, 2100 Capitol Ave, Suite 310", "attendees": [], "attendee_responses": {}}, {"event_id": "d2f1c8a3b9e7f6d4c0a8b5e1", "title": "Farmers Market - 8th & W", "start_datetime": "2026-04-11T17:00:00Z", "end_datetime": "2026-04-11T19:00:00Z", "organizer": "", "tag": "personal", "description": "", "location": "Midtown Farmers Market, 8th & W Street", "attendees": ["Soomin Choi", "Hana Choi"], "attendee_responses": {}}, {"event_id": "a5baf5d5bc0fbdff3f7ae017", "title": "Dental conference dinner - Hyatt Regency", "start_datetime": "2026-04-12T03:30:00Z", "end_datetime": "2026-04-12T05:30:00Z", "organizer": "", "tag": "work", "description": "SDDS networking dinner", "location": "Hyatt Regency Sacramento, 1209 L Street", "attendees": [], "attendee_responses": {}}, {"event_id": "9a3d5c7e1f4b6a8d2c0e3f5b", "title": "Gym - weights 6:30-9:30 PM", "start_datetime": "2026-04-15T03:30:00Z", "end_datetime": "2026-04-15T06:30:00Z", "organizer": "", "tag": "personal", "description": "Push day \u2014 close-grip bench", "location": "24 Hour Fitness", "attendees": [], "attendee_responses": {}}, {"event_id": "d7ce0c44b9e9a8d9498f5129", "title": "Dr. Patel", "start_datetime": "2026-04-17T03:00:00Z", "end_datetime": "2026-04-17T04:00:00Z", "organizer": "", "tag": "personal", "description": "Weekly session \u2014 practice expansion stress", "location": "Capitol Wellness Associates, 2100 Capitol Ave, Suite 310", "attendees": [], "attendee_responses": {}}, {"event_id": "b3e6d0a2c5f9d1f4a7b0c3e6", "title": "Spring cleaning - garage and closets", "start_datetime": "2026-04-19T17:00:00Z", "end_datetime": "2026-04-19T23:00:00Z", "organizer": "", "tag": "personal", "description": "Clean out garage and hall closet. Sort donations for Goodwill.", "location": "2415 T Street", "attendees": ["Soomin Choi"], "attendee_responses": {}}, {"event_id": "9c656b7ecaacb92dcc76358b", "title": "Gym - weights 6:30-9:30 PM", "start_datetime": "2026-04-22T03:30:00Z", "end_datetime": "2026-04-22T06:30:00Z", "organizer": "", "tag": "personal", "description": "Pull day \u2014 chin-ups + rows", "location": "24 Hour Fitness", "attendees": [], "attendee_responses": {}}, {"event_id": "ae2c7d476571a252970f8e13", "title": "Dr. Patel", "start_datetime": "2026-04-24T03:00:00Z", "end_datetime": "2026-04-24T04:00:00Z", "organizer": "", "tag": "personal", "description": "Weekly session \u2014 interpersonal patterns", "location": "Capitol Wellness Associates, 2100 Capitol Ave, Suite 310", "attendees": [], "attendee_responses": {}}, {"event_id": "3e11774b187505ef62acb0e5", "title": "Gym - weights 6:30-9:30 PM", "start_datetime": "2026-04-29T03:30:00Z", "end_datetime": "2026-04-29T06:30:00Z", "organizer": "", "tag": "personal", "description": "Leg day \u2014 leg press + calves", "location": "24 Hour Fitness", "attendees": [], "attendee_responses": {}}, {"event_id": "18aac81064362fc368e0aa5d", "title": "Dr. Patel", "start_datetime": "2026-05-01T03:00:00Z", "end_datetime": "2026-05-01T04:00:00Z", "organizer": "", "tag": "personal", "description": "Weekly session \u2014 self-care audit", "location": "Capitol Wellness Associates, 2100 Capitol Ave, Suite 310", "attendees": [], "attendee_responses": {}}, {"event_id": "c42d89791d1dc83eac460554", "title": "Dinner at Byung's", "start_datetime": "2026-05-04T03:00:00Z", "end_datetime": "2026-05-04T05:00:00Z", "organizer": "", "tag": "personal", "description": "Quick weeknight \u2014 leftovers + banchan", "location": "Byung Park's residence", "attendees": ["Soomin Choi", "Byung Park", "Hana Choi"], "attendee_responses": {}}, {"event_id": "ded6b9947dbadcae1741e4af", "title": "Gym - weights 6:30-9:30 PM", "start_datetime": "2026-05-06T03:30:00Z", "end_datetime": "2026-05-06T06:30:00Z", "organizer": "", "tag": "personal", "description": "Push day \u2014 landmine press", "location": "24 Hour Fitness", "attendees": [], "attendee_responses": {}}, {"event_id": "45a4061e30204d1ca1b458c4", "title": "Dr. Patel", "start_datetime": "2026-05-08T03:00:00Z", "end_datetime": "2026-05-08T04:00:00Z", "organizer": "", "tag": "personal", "description": "Weekly session \u2014 symptom tracking review", "location": "Capitol Wellness Associates, 2100 Capitol Ave, Suite 310", "attendees": [], "attendee_responses": {}}, {"event_id": "d6e2f8a4b0c1d7e3f9a5b1c2", "title": "Mother's Day Brunch - Canon", "start_datetime": "2026-05-11T17:30:00Z", "end_datetime": "2026-05-11T19:00:00Z", "organizer": "", "tag": "personal", "description": "Reservation for 4. Highchair for Hana.", "location": "Canon, 1112 R Street, Sacramento", "attendees": ["Soomin Choi", "Hana Choi", "Byung Park"], "attendee_responses": {}}, {"event_id": "0b4e6d8f2a5c7b9e3d1f4a6c", "title": "Gym - weights 6:30-9:30 PM", "start_datetime": "2026-05-13T03:30:00Z", "end_datetime": "2026-05-13T06:30:00Z", "organizer": "", "tag": "personal", "description": "Pull day \u2014 t-bar rows", "location": "24 Hour Fitness", "attendees": [], "attendee_responses": {}}, {"event_id": "79c8e55149f2d87c8b986f1c", "title": "Dr. Patel \u2014 Capitol Wellness 6:00 PM", "start_datetime": "2026-05-15T04:00:00Z", "end_datetime": "2026-05-15T05:00:00Z", "organizer": "", "tag": "personal", "description": "Weekly session", "location": "Capitol Wellness Associates, 2100 Capitol Ave, Suite 310", "attendees": [], "attendee_responses": {}}, {"event_id": "1c5f7e9a3b6d8c0f4e2a5b7d", "title": "SCC Spring Concert", "start_datetime": "2026-05-17T04:00:00Z", "end_datetime": "2026-05-17T06:30:00Z", "organizer": "", "tag": "personal", "description": "Call time 5:30 PM. Two front-row tickets.", "location": "First United Methodist Church, 2101 L Street", "attendees": [], "attendee_responses": {}}, {"event_id": "96384cc03f9f7a2f068340db", "title": "Family photos - Capitol Park 9 AM", "start_datetime": "2026-05-18T16:00:00Z", "end_datetime": "2026-05-18T17:30:00Z", "organizer": "", "tag": "personal", "description": "Photo session with Sarah Kim. Rose garden entrance, 15th & L Street.", "location": "Capitol Park, Sacramento", "attendees": ["Soomin Choi", "Hana Choi"], "attendee_responses": {}}, {"event_id": "405c176230c2d89eded645dd", "title": "Gym - weights 6:30-9:30 PM", "start_datetime": "2026-05-20T03:30:00Z", "end_datetime": "2026-05-20T06:30:00Z", "organizer": "", "tag": "personal", "description": "Leg day \u2014 Bulgarian split squats", "location": "24 Hour Fitness", "attendees": [], "attendee_responses": {}}, {"event_id": "629bb05f69675a9a63f033f1", "title": "Dr. Patel", "start_datetime": "2026-05-22T03:00:00Z", "end_datetime": "2026-05-22T04:00:00Z", "organizer": "", "tag": "personal", "description": "Weekly session \u2014 relapse-prevention discussion", "location": "Capitol Wellness Associates, 2100 Capitol Ave, Suite 310", "attendees": [], "attendee_responses": {}}, {"event_id": "8e6a2c5d9f7b1e3c0a4d8f65", "title": "Pick up dry cleaning - Capitol Cleaners", "start_datetime": "2026-05-22T16:00:00Z", "end_datetime": "2026-05-22T16:30:00Z", "organizer": "", "tag": "personal", "description": "", "location": "Capitol Cleaners", "attendees": [], "attendee_responses": {}}, {"event_id": "9f7b3d6e0a8c2f4d1b5e9a76", "title": "Anniversary dinner - Localis 7:30 PM", "start_datetime": "2026-05-24T02:30:00Z", "end_datetime": "2026-05-24T05:00:00Z", "organizer": "", "tag": "personal", "description": "5th wedding anniversary", "location": "Localis, 2031 S Street", "attendees": [], "attendee_responses": {}}, {"event_id": "14fdbcb75af24abf857ecc6f", "title": "Gym - weights 6:30-9:30 PM", "start_datetime": "2026-05-27T03:30:00Z", "end_datetime": "2026-05-27T06:30:00Z", "organizer": "", "tag": "personal", "description": "Push day \u2014 overhead carries", "location": "24 Hour Fitness", "attendees": [], "attendee_responses": {}}, {"event_id": "dd80a4ab633878fd1453618f", "title": "Dr. Patel", "start_datetime": "2026-05-29T03:00:00Z", "end_datetime": "2026-05-29T04:00:00Z", "organizer": "", "tag": "personal", "description": "Weekly session \u2014 long-term goal review", "location": "Capitol Wellness Associates, 2100 Capitol Ave, Suite 310", "attendees": [], "attendee_responses": {}}, {"event_id": "542acde970254e7ca6406ba67437e83f", "title": "6-Month Financial Plan Review", "start_datetime": "2026-11-22T10:00:00Z", "end_datetime": "2026-11-22T11:00:00Z", "organizer": "", "tag": "personal", "description": "6 months since starting the savings plan. Full milestone review \u2014 see financial-plan-2026.md and yearly-savings-plan-2026.md. Also: Covered California open enrollment starts Nov 1 \u2014 shop health insurance before Dec 15 deadline.", "location": "Home", "attendees": [], "attendee_responses": {}}]}